ptfkit/__init__.py
ptfkit/_core.cpython-314-aarch64-linux-musl.so
ptfkit/_core.py
ptfkit/aimrun2009.py
ptfkit/jabro1992.py
ptfkit/li2007.py
ptfkit/puckett1985.py
ptfkit/py.typed
ptfkit/qiao2018.py
ptfkit/ramos2023.py
ptfkit/rawls1982.py
ptfkit/rawls1983.py
ptfkit/rawls1985.py
ptfkit/santra2008.py
ptfkit/tiwary2014.py
ptfkit/wang2012.py
ptfkit-0.1.0.dist-info/METADATA
ptfkit-0.1.0.dist-info/WHEEL
ptfkit-0.1.0.dist-info/top_level.txt
ptfkit-0.1.0.dist-info/RECORD
ptfkit-0.1.0.dist-info/licenses/LICENSE
