Metadata-Version: 2.4
Name: ptfkit
Version: 0.1.0
Summary: Pedotransfer functions for estimating soil hydraulic properties
Author-email: Dmitry Fomin <fomin_ds@esoil.ru>, Petr Shumilin <shumpet03@yandex.ru>, Kirill Tolstygin <tolstygin_kd@esoil.ru>, Petr Tsymbarovich <tpr@esoil.ru>
Maintainer-email: Petr Tsymbarovich <tpr@esoil.ru>, Kirill Tolstygin <tolstygin_kd@esoil.ru>
License-Expression: MIT
Project-URL: Repository, https://github.com/AgroDT/ptfkit
Project-URL: Issues, https://github.com/AgroDT/ptfkit/issues
Project-URL: Documentation, https://agrodt.github.io/ptfkit/
Classifier: Development Status :: 4 - Beta
Classifier: Intended Audience :: Science/Research
Classifier: Natural Language :: English
Classifier: Operating System :: OS Independent
Classifier: Programming Language :: Cython
Classifier: Programming Language :: Python :: 3.10
Classifier: Programming Language :: Python :: 3.11
Classifier: Programming Language :: Python :: 3.12
Classifier: Programming Language :: Python :: 3.13
Classifier: Programming Language :: Python :: 3
Classifier: Programming Language :: Python
Classifier: Topic :: Scientific/Engineering :: Hydrology
Classifier: Topic :: Scientific/Engineering
Requires-Python: >=3.10
License-File: LICENSE
Requires-Dist: numpy<3,>=2.0
Dynamic: license-file
